semantic_release_naas_test/__init__.py
semantic_release_naas_test/main.py
semantic_release_naas_test-1.3.0.dist-info/METADATA
semantic_release_naas_test-1.3.0.dist-info/WHEEL
semantic_release_naas_test-1.3.0.dist-info/top_level.txt
semantic_release_naas_test-1.3.0.dist-info/RECORD
